climatik/__init__.py
climatik/py.typed
climatik-0.4.2.dist-info/COPYING
climatik-0.4.2.dist-info/METADATA
climatik-0.4.2.dist-info/WHEEL
climatik-0.4.2.dist-info/top_level.txt
climatik-0.4.2.dist-info/RECORD
