Metadata-Version: 2.1
Name: climatik
Version: 0.4.2
Summary: Create command line interface from function definitions.
Home-page: https://git.sr.ht/~fabrixxm/climatik
Author: Fabio Comuni
Author-email: fabrix.xm+pypi@gmail.com
License: GPLv3+
Classifier: Development Status :: 4 - Beta
Classifier: Intended Audience :: Developers
Classifier: License :: OSI Approved :: GNU General Public License v3 or later (GPLv3+)
Classifier: Programming Language :: Python :: 3
Classifier: Programming Language :: Python :: 3.8
Classifier: Programming Language :: Python :: 3.9
Requires-Python: >=3.8
License-File: COPYING
Provides-Extra: autocomplete
Requires-Dist: argcomplete ; extra == 'autocomplete'
Provides-Extra: dev
Requires-Dist: nose2 ; extra == 'dev'
Requires-Dist: mypy ; extra == 'dev'
Requires-Dist: twine ; extra == 'dev'
Requires-Dist: wheel ; extra == 'dev'
